<?xml version="1.0" encoding="utf-8"?>
<modsCollection xmlns="http://www.loc.gov/mods/v3" xmlns:xlink="http://www.w3.org/1999/xlink" xmlns:xsi="http://www.w3.org/2001/XMLSchema-instance" xsi:schemaLocation="http://www.loc.gov/mods/v3 http://www.loc.gov/standards/mods/v3/mods-3-7.xsd">
<mods version="3.7">
      <titleInfo>
         <title>Selecting rail properties for improvement</title>
         <subTitle>a plan for analysis</subTitle>
      </titleInfo>
      <name type="personal" usage="primary">
         <namePart>Schofer, R. E.</namePart>
      </name>
      <name type="personal">
         <namePart>Schofer, R. E.</namePart>
      </name>
      <name type="personal">
         <namePart>Gilsinn, J. F.</namePart>
      </name>
      <name type="personal" xlink:href="https://id.loc.gov/authorities/names/n2013040639">
         <namePart>Hall, W. G.,</namePart>
         <namePart type="date">active 1917</namePart>
         <nameIdentifier>https://id.loc.gov/authorities/names/n2013040639</nameIdentifier>
      </name>
      <name type="personal" xlink:href="https://id.loc.gov/authorities/names/n82008536">
         <namePart>Johnson, C. R.</namePart>
         <nameIdentifier>https://id.loc.gov/authorities/names/n82008536</nameIdentifier>
      </name>
      <name type="personal" xlink:href="https://id.loc.gov/authorities/names/n88094768">
         <namePart>McLynn, J. M.,</namePart>
         <namePart type="date">1925-</namePart>
         <nameIdentifier>https://id.loc.gov/authorities/names/n88094768</nameIdentifier>
      </name>
      <name type="personal" xlink:href="https://id.loc.gov/authorities/names/no2009021554">
         <namePart>Watkins, R. H.</namePart>
         <nameIdentifier>https://id.loc.gov/authorities/names/no2009021554</nameIdentifier>
      </name>
      <name type="corporate" xlink:href="https://id.loc.gov/authorities/names/n88112126">
         <namePart>National Institute of Standards and Technology (U.S.)</namePart>
         <nameIdentifier>https://id.loc.gov/authorities/names/n88112126</nameIdentifier>
      </name>
      <typeOfResource>text</typeOfResource>
      <genre authority="marcgt">encyclopedia</genre>
      <genre authority="rdacontent">text</genre>
      <genre authority="lcgft">Technical reports.</genre>
      <genre authority="fast">Technical reports.</genre>
      <originInfo>
         <place>
            <placeTerm type="code" authority="marccountry">ot</placeTerm>
         </place>
         <dateIssued encoding="marc">1980</dateIssued>
         <issuance>monographic</issuance>
      </originInfo>
      <originInfo eventType="publisher">
         <place>
            <placeTerm type="text">Gaithersburg, MD :</placeTerm>
         </place>
         <publisher>U.S. Dept. of Commerce, National Institute of Standards and
                Technology; </publisher>
         <dateIssued>1980.</dateIssued>
      </originInfo>
      <physicalDescription>
         <form authority="marcform">print</form>
         <form type="carrier" authority="rdacarrier">online resource</form>
         <extent>1 online resource.</extent>
      </physicalDescription>
      <note type="statement of responsibility">R. E. Schofer; J. F. Gilsinn; W. G. Hall; C. R. Johnson; J. M.
                McLynn; R. H. Watkins.</note>
      <note>1980.</note>
      <note>Title from PDF title page.</note>
      <note type="bibliography">Includes bibliographical references.</note>
      <note type="system details">Mode of access: World Wide Web.</note>
      <note type="system details">Systems requirements: Adobe Acrobat PDF reader.</note>
      <location>
         <url displayLabel="electronic resource" usage="primary display">https://doi.org/10.6028/NBS.IR.79-1724</url>
      </location>
      <relatedItem type="series">
         <titleInfo>
            <title>NBSIR; NBS IR; NBS interagency report; NBS internal report
</title>
            <partNumber>79-1724</partNumber>
         </titleInfo>
      </relatedItem>
      <identifier type="oclc">1312491402</identifier>
      <recordInfo>
         <descriptionStandard>rda</descriptionStandard>
         <recordContentSource authority="marcorg">NBS</recordContentSource>
         <recordCreationDate encoding="marc">160309</recordCreationDate>
         <recordChangeDate encoding="iso8601">20160309011333.0</recordChangeDate>
         <recordIdentifier>991000119139708106</recordIdentifier>
         <recordOrigin>Converted from MARCXML to MODS version 3.7 using MARC21slim2MODS3-7.xsl
				(Revision 1.140 20200717)</recordOrigin>
         <languageOfCataloging>
            <languageTerm authority="iso639-2b" type="code">eng</languageTerm>
         </languageOfCataloging>
      </recordInfo>
   </mods></modsCollection>
