<?xml version="1.0" encoding="utf-8"?>
<modsCollection xmlns="http://www.loc.gov/mods/v3" xmlns:xlink="http://www.w3.org/1999/xlink" xmlns:xsi="http://www.w3.org/2001/XMLSchema-instance" xsi:schemaLocation="http://www.loc.gov/mods/v3 http://www.loc.gov/standards/mods/v3/mods-3-7.xsd">
<mods version="3.7">
      <titleInfo>
         <title>Status report on the second round of the SHA-3 cryptographic hash
                algorithm competition</title>
      </titleInfo>
      <name type="personal" usage="primary">
         <namePart>Turan, Meltem Sonmez.</namePart>
      </name>
      <name type="personal">
         <namePart>Turan, Meltem Sonmez.</namePart>
      </name>
      <name type="personal">
         <namePart>Perlner, Ray.</namePart>
      </name>
      <name type="personal" xlink:href="https://id.loc.gov/authorities/names/n91102724">
         <namePart>Bassham, Lawrence E.</namePart>
         <nameIdentifier>https://id.loc.gov/authorities/names/n91102724</nameIdentifier>
      </name>
      <name type="personal" xlink:href="https://id.loc.gov/authorities/names/n92104702">
         <namePart>Burr, William.</namePart>
         <nameIdentifier>https://id.loc.gov/authorities/names/n92104702</nameIdentifier>
      </name>
      <name type="personal">
         <namePart>Chang, Donghoon.</namePart>
      </name>
      <name type="personal" xlink:href="https://id.loc.gov/authorities/names/nr94020302">
         <namePart>Zhang, Shuoren.</namePart>
         <nameIdentifier>https://id.loc.gov/authorities/names/nr94020302</nameIdentifier>
      </name>
      <name type="personal">
         <namePart>Dworkin, Morris J.</namePart>
      </name>
      <name type="personal">
         <namePart>Kelsey, John M.</namePart>
      </name>
      <name type="personal">
         <namePart>Paul, Souradyuti.</namePart>
      </name>
      <name type="personal" xlink:href="https://id.loc.gov/authorities/names/n2008037022">
         <namePart>Peralta, René.</namePart>
         <nameIdentifier>https://id.loc.gov/authorities/names/n2008037022</nameIdentifier>
      </name>
      <name type="corporate" xlink:href="https://id.loc.gov/authorities/names/no2008015449">
         <namePart>Information Technology Laboratory (National Institute of Standards
                and Technology).</namePart>
         <namePart>Computer Security Division.</namePart>
         <nameIdentifier>https://id.loc.gov/authorities/names/no2008015449</nameIdentifier>
      </name>
      <typeOfResource>text</typeOfResource>
      <genre authority="marcgt">encyclopedia</genre>
      <genre authority="rdacontent">text</genre>
      <genre authority="lcgft">Technical reports.</genre>
      <genre authority="fast">Technical reports.</genre>
      <originInfo>
         <place>
            <placeTerm type="code" authority="marccountry">ot</placeTerm>
         </place>
         <dateIssued encoding="marc">2011</dateIssued>
         <issuance>monographic</issuance>
      </originInfo>
      <originInfo eventType="publisher">
         <place>
            <placeTerm type="text">Gaithersburg, MD :</placeTerm>
         </place>
         <publisher>U.S. Dept. of Commerce, National Institute of Standards and
                Technology; </publisher>
         <dateIssued>2011.</dateIssued>
      </originInfo>
      <physicalDescription>
         <form authority="marcform">print</form>
         <form type="media" authority="rdamedia">computer</form>
         <form type="carrier" authority="rdacarrier">online resource</form>
         <extent>1 online resource.</extent>
      </physicalDescription>
      <note type="statement of responsibility">Meltem Sonmez Turan; Ray Perlner; Lawrence E. Bassham; William Burr;
                Donghoon Chang; Shu-jen Chang; Morris J. Dworkin; John M. Kelsey; Souradyuti Paul;
                Rene Peralta.</note>
      <note>2011.</note>
      <note>Title from PDF title page.</note>
      <note type="bibliography">Includes bibliographical references.</note>
      <note type="system details">Mode of access: World Wide Web.</note>
      <note type="system details">Systems requirements: Adobe Acrobat PDF reader.</note>
      <location>
         <url displayLabel="electronic resource" usage="primary display">https://doi.org/10.6028/NIST.IR.7764</url>
      </location>
      <relatedItem type="series">
         <titleInfo>
            <title>NISTIR; NIST IR; NIST interagency report; NIST internal report
</title>
            <partNumber>7764</partNumber>
         </titleInfo>
      </relatedItem>
      <identifier type="oclc">947049746</identifier>
      <recordInfo>
         <descriptionStandard>rda</descriptionStandard>
         <recordContentSource authority="marcorg">NBS</recordContentSource>
         <recordCreationDate encoding="marc">160421</recordCreationDate>
         <recordChangeDate encoding="iso8601">20160421112352.0</recordChangeDate>
         <recordIdentifier>991000147309708106</recordIdentifier>
         <recordOrigin>Converted from MARCXML to MODS version 3.7 using MARC21slim2MODS3-7.xsl
				(Revision 1.140 20200717)</recordOrigin>
         <languageOfCataloging>
            <languageTerm authority="iso639-2b" type="code">eng</languageTerm>
         </languageOfCataloging>
      </recordInfo>
   </mods></modsCollection>
